runtimedocs/__init__.py
runtimedocs/core.py
runtimedocs/helpers.py
runtimedocs-1.0.2.dist-info/METADATA
runtimedocs-1.0.2.dist-info/RECORD
runtimedocs-1.0.2.dist-info/WHEEL
runtimedocs-1.0.2.dist-info/top_level.txt
