Metadata-Version: 2.1
Name: runtimedocs
Version: 1.0.2
Summary: Understanding how your code behaves at runtime made simple
Home-page: https://github.com/junteudjio/runtimedocs
Author: Junior Teudjio
Author-email: jun.teudjio@gmail.com
License: MIT
Platform: UNKNOWN
Classifier: Development Status :: 5 - Production/Stable
Classifier: Intended Audience :: Developers
Classifier: License :: OSI Approved :: MIT License
Classifier: Operating System :: OS Independent
Classifier: Topic :: Software Development :: Libraries
Classifier: Topic :: Utilities
Classifier: Programming Language :: Python :: 3
Classifier: Programming Language :: Python :: 3.4
Classifier: Programming Language :: Python :: 3.5
Classifier: Programming Language :: Python :: 3.6
Classifier: Programming Language :: Python :: 3.7
